distributions/Binomialdistribution.py
distributions/Gaussiandistribution.py
distributions/Generaldistribution.py
distributions/__init__.py
distributions_KR-0.1.dist-info/DESCRIPTION.rst
distributions_KR-0.1.dist-info/METADATA
distributions_KR-0.1.dist-info/RECORD
distributions_KR-0.1.dist-info/WHEEL
distributions_KR-0.1.dist-info/metadata.json
distributions_KR-0.1.dist-info/top_level.txt
